{"metadata":{"version":"1.0.0","type":"Object","generator":"zhouzf"},"materials":[{"color":"0xffffff","shininess":0,"emissiveIntensity":0,"uuid":"D8126044-0270-4ADE-9D5E-B95983CA10A3","name":"Default-Material","type":"MeshLambertMaterial","side":0,"opacity":1,"transparent":false,"alphaTest":0}],"geometries":[{"data":{"index":{"itemSize":1,"type":"Uint16Array","array":[0,3,2,0,1,3,8,5,4,8,9,5,10,7,6,10,11,7,12,14,13,12,15,14,16,18,17,16,19,18,20,22,21,20,23,22]},"attributes":{"position":{"itemSize":3,"type":"Float32Array","array":[0.5,-0.5,-0.5,-0.5,-0.5,-0.5,0.5,0.5,-0.5,-0.5,0.5,-0.5,0.5,0.5,0.5,-0.5,0.5,0.5,0.5,-0.5,0.5,-0.5,-0.5,0.5,0.5,0.5,-0.5,-0.5,0.5,-0.5,0.5,0.5,0.5,-0.5,0.5,0.5,0.5,-0.5,0.5,0.5,-0.5,-0.5,-0.5,-0.5,-0.5,-0.5,-0.5,0.5,-0.5,-0.5,-0.5,-0.5,0.5,-0.5,-0.5,0.5,0.5,-0.5,-0.5,0.5,0.5,-0.5,0.5,0.5,0.5,0.5,0.5,0.5,-0.5,0.5,-0.5,-0.5]},"normal":{"itemSize":3,"type":"Float32Array","array":[0,0,-1,0,0,-1,0,0,-1,0,0,-1,0,1,0,0,1,0,0,0,1,0,0,1,0,1,0,0,1,0,0,0,1,0,0,1,0,-1,0,0,-1,0,0,-1,0,0,-1,0,-1,0,0,-1,0,0,-1,0,0,-1,0,0,1,0,0,1,0,0,1,0,0,1,0,0]},"color":{"itemSize":3,"type":"Float32Array","array":[]},"uv":{"itemSize":2,"type":"Float32Array","array":[0,0,1,0,0,1,1,1,0,1,1,1,0,1,1,1,0,0,1,0,0,0,1,0,0,0,0,1,1,1,1,0,0,0,0,1,1,1,1,0,0,0,0,1,1,1,1,0]},"uv2":{"itemSize":2,"type":"Float32Array","array":[0.691,0.3472,0.9967,0.3472,0.691,0.6528,0.9967,0.6528,0.3097,0.3472,0.0041,0.3472,0.3472,0.6528,0.6528,0.6528,0.3097,0.6528,0.0041,0.6528,0.3472,0.3472,0.6528,0.3472,0.3472,0.0041,0.3472,0.3097,0.6528,0.3097,0.6528,0.0041,0.6903,0.3097,0.9959,0.3097,0.9959,0.0041,0.6903,0.0041,0.3097,0.0041,0.0041,0.0041,0.0041,0.3097,0.3097,0.3097]}}},"uuid":"a5554939-e30c-4a09-89eb-2f3758e7022e","type":"BufferGeometry"}],"object":{"visible":true,"geometry":"a5554939-e30c-4a09-89eb-2f3758e7022e","material":"D8126044-0270-4ADE-9D5E-B95983CA10A3","castShadow":true,"receiveShadow":true,"userdata":{"center":[0,0,0],"size":[1,1,1],"type":"BoxCollider"},"uuid":"7acd4411-4eb3-47ef-a15e-691d01b429bb","name":"Cube","type":"Mesh","matrix":[1,0,0,0,0,1,0,0,0,0,1,0,0,0,0,1]},"images":[],"textures":[]}